{
    "tweet_id": "1325122200920317953",
    "computation_time": 58.34336185455322,
    "model": "gemma3:27b",
    "created_at": "2025-08-07T20:37:16.955819922Z",
    "response": {
        "confidence": 85,
        "analysis": "The image displays a heatmap representing the number of COVID-19 cases by county in Ireland over a 14-day period. Each cell in the heatmap corresponds to a specific county and date (from Oct 26th to Nov 8th). The color intensity of each cell represents the number of cases; darker shades indicate higher case counts, while lighter shades indicate lower case counts. The image includes a color scale indicating the case count range for each color. \n\nThe heatmap covers the following dates: October 26th, October 28th, October 30th, November 1st, November 3rd, November 6th, and November 8th. The counties listed along the y-axis (from top to bottom) include: Donegal, Cavan, Monaghan, Leitrim, Sligo, Mayo, Galway, Roscommon, Longford, Westmeath, Offaly, Laois, Kildare, Wicklow, Dublin, Louth, Meath, Cork, Kerry, Limerick, Tipperary, Clare, Waterford, Wexford, and Carlow.\n\nSeveral patterns are visible: Dublin consistently has the highest number of cases across all dates, indicated by the darkest color shading. Other counties with consistently high case numbers include Cork, Limerick, Galway, and Louth. Several counties consistently show very low case numbers, with lighter shades indicating fewer than 5 cases per day. A notable upward trend seems to be visible towards the later dates (Nov 6th, Nov 8th) in several counties, indicating a possible increase in cases during that time frame. The overall trend suggests that case distribution is not uniform across all counties; certain urban centers (Dublin, Cork) consistently have higher numbers.\n\nThe likely message communicated by the visualization is to illustrate the geographic distribution of COVID-19 cases in Ireland over a 14-day period and highlight the counties with the highest case counts. This information is crucial for public health officials to focus their resources and implement targeted interventions. The visualization supports tracking the progression of cases and identifying potential hotspots.\n\nBased on my analysis, it's clear that case concentrations are not evenly spread throughout Ireland. The consistently high numbers in Dublin and Cork suggest that these areas were significant contributors to the overall case count during the period shown. The increase in cases observed in the later dates warrants further investigation to understand the drivers of the trend and prevent further spread. The visualization provides a concise and visually effective way to communicate complex epidemiological data.\n\nConfidence Score Justification: The image is reasonably clear, and the caption directly relates to the content. The color scheme is effectively used to represent the magnitude of cases. The data appears to be organized and presented in a standard heatmap format. I am confident in my interpretation because the visualized data is straightforward and easy to understand, and there's minimal ambiguity. However, the exact numbers within each cell aren't displayed, which limits the precision of the analysis. This contributes to a slightly lower confidence score."
    },
    "done": true,
    "done_reason": "stop",
    "context": [
        105,
        2364,
        107,
        236840,
        3024,
        236772,
        236771,
        236842,
        109,
        3048,
        659,
        2238,
        614,
        2471,
        600,
        6097,
        886,
        653,
        919,
        151289,
        532,
        614,
        34043,
        44358,
        236761,
        108,
        818,
        44358,
        563,
        236787,
        13659,
        59372,
        236770,
        236819,
        750,
        1591,
        3636,
        684,
        10028,
        236764,
        1774,
        236743,
        236770,
        236812,
        2668,
        3056,
        108,
        11069,
        4209,
        563,
        531,
        236787,
        107,
        255968,
        236770,
        236761,
        255968,
        115863,
        506,
        3004,
        529,
        506,
        2471,
        532,
        506,
        44358,
        236761,
        107,
        255968,
        236778,
        236761,
        255968,
        82858,
        528,
        8052,
        1144,
        506,
        151289,
        2754,
        236761,
        49644,
        27570,
        236764,
        15067,
        236764,
        9935,
        236764,
        12669,
        236764,
        653,
        24786,
        1262,
        3298,
        236761,
        107,
        255968,
        236800,
        236761,
        255968,
        156022,
        506,
        151289,
        236787,
        2900,
        19317,
        740,
        577,
        9710,
        236881,
        2900,
        563,
        506,
        4547,
        3618,
        653,
        12882,
        506,
        151289,
        659,
        40122,
        236881,
        107,
        255968,
        236812,
        236761,
        255968,
        93000,
        822,
        1852,
        12882,
        2721,
        580,
        822,
        3671,
        236761,
        107,
        255968,
        236810,
        236761,
        255968,
        21796,
        822,
        10805,
        528,
        822,
        16823,
        580,
        496,
        5559,
        699,
        236743,
        236771,
        531,
        236743,
        236770,
        236771,
        236771,
        236764,
        1298,
        236743,
        236771,
        2820,
        999,
        2217,
        12081,
        657,
        784,
        236919,
        532,
        236743,
        236770,
        236771,
        236771,
        2820,
        999,
        133299,
        12081,
        1827,
        5393,
        1891,
        822,
        10805,
        6317,
        568,
        236744,
        236761,
        236759,
        1126,
        2471,
        29972,
        236764,
        57352,
        528,
        1262,
        236764,
        25000,
        607,
        44358,
        236764,
        4044,
        7476,
        108,
        3912,
        13868,
        236764,
        3582,
        236764,
        532,
        18997,
        528,
        822,
        15569,
        236761,
        39874,
        46020,
        11461,
        236761,
        108,
        7925,
        528,
        10434,
        6518,
        236764,
        1133,
        672,
        236787,
        107,
        236782,
        107,
        138,
        236775,
        58578,
        1083,
        623,
        217349,
        6317,
        699,
        4209,
        1523,
        236743,
        236810,
        5899,
        1590,
        827,
        107,
        138,
        236775,
        28263,
        1083,
        623,
        17993,
        9813,
        3671,
        3072,
        568,
        8071,
        3298,
        236743,
        236770,
        236964,
        236810,
        236768,
        5899,
        1590,
        827,
        107,
        236783,
        108,
        6294,
        711,
        3204,
        4658,
        1663,
        1032,
        1082,
        506,
        8373,
        2495,
        236761,
        3574,
        711,
        1879,
        20686,
        3723,
        657,
        506,
        6534,
        236761,
        107,
        106,
        107,
        105,
        4368,
        107,
        2717,
        3723,
        107,
        236782,
        107,
        138,
        236775,
        58578,
        1083,
        236743,
        236828,
        236810,
        236764,
        107,
        138,
        236775,
        28263,
        1083,
        623,
        818,
        2471,
        19365,
        496,
        153819,
        13855,
        506,
        1548,
        529,
        7767,
        236772,
        236770,
        236819,
        3636,
        684,
        10028,
        528,
        13531,
        1024,
        496,
        236743,
        236770,
        236812,
        236772,
        1496,
        2846,
        236761,
        7714,
        2145,
        528,
        506,
        153819,
        17671,
        531,
        496,
        3530,
        10028,
        532,
        3433,
        568,
        2543,
        4905,
        236743,
        236778,
        236825,
        594,
        531,
        8934,
        236743,
        236828,
        594,
        769,
        669,
        2258,
        12732,
        529,
        1546,
        2145,
        9282,
        506,
        1548,
        529,
        3636,
        236793,
        45356,
        31868,
        10128,
        3715,
        1624,
        18558,
        236764,
        1651,
        28279,
        31868,
        10128,
        3718,
        1624,
        18558,
        236761,
        669,
        2471,
        5132,
        496,
        2258,
        5559,
        17674,
        506,
        1624,
        1527,
        2644,
        573,
        1546,
        2258,
        236761,
        621,
        236749,
        236785,
        193983,
        153819,
        13526,
        506,
        2269,
        14069,
        236787,
        6198,
        236743,
        236778,
        236825,
        594,
        236764,
        6198,
        236743,
        236778,
        236828,
        594,
        236764,
        6198,
        236743,
        236800,
        236771,
        594,
        236764,
        6243,
        236743,
        236770,
        540,
        236764,
        6243,
        236743,
        236800,
        7221,
        236764,
        6243,
        236743,
        236825,
        594,
        236764,
        532,
        6243,
        236743,
        236828,
        594,
        236761,
        669,
        25432,
        9456,
        3008,
        506,
        570,
        236772,
        11569,
        568,
        2543,
        1903,
        531,
        5944,
        236768,
        3204,
        236787,
        175285,
        236764,
        184829,
        236764,
        4325,
        93757,
        236764,
        115271,
        4966,
        236764,
        555,
        194329,
        236764,
        53324,
        236764,
        103772,
        236764,
        13615,
        11147,
        236764,
        8099,
        5297,
        236764,
        4844,
        1336,
        651,
        236764,
        5357,
        5626,
        236764,
        2774,
        6958,
        236764,
        189136,
        733,
        236764,
        231811,
        236764,
        27071,
        236764,
        639,
        2567,
        236764,
        3060,
        651,
        236764,
        57450,
        236764,
        64314,
        236764,
        144118,
        236764,
        193559,
        835,
        236764,
        65837,
        236764,
        154491,
        236764,
        215708,
        236764,
        532,
        3331,
        976,
        6810,
        236749,
        236785,
        236749,
        34823,
        9935,
        659,
        11325,
        236787,
        27071,
        22541,
        815,
        506,
        7310,
        1548,
        529,
        3636,
        3418,
        784,
        14069,
        236764,
        10117,
        684,
        506,
        106321,
        2258,
        78553,
        236761,
        7067,
        25432,
        607,
        22541,
        1494,
        1624,
        4945,
        3204,
        57450,
        236764,
        144118,
        236764,
        103772,
        236764,
        532,
        639,
        2567,
        236761,
        22624,
        25432,
        22541,
        1407,
        1401,
        2708,
        1624,
        4945,
        236764,
        607,
        28279,
        31868,
        17674,
        18661,
        1082,
        236743,
        236810,
        3636,
        810,
        1719,
        236761,
        562,
        24786,
        31097,
        7003,
        5072,
        531,
        577,
        11325,
        5645,
        506,
        3209,
        14069,
        568,
        29097,
        236743,
        236825,
        594,
        236764,
        8934,
        236743,
        236828,
        594,
        236768,
        528,
        3131,
        25432,
        236764,
        17674,
        496,
        2653,
        3553,
        528,
        3636,
        1913,
        600,
        990,
        5528,
        236761,
        669,
        6782,
        7003,
        12205,
        600,
        1624,
        5296,
        563,
        711,
        9406,
        3418,
        784,
        25432,
        236793,
        2953,
        11321,
        16545,
        568,
        177515,
        236764,
        57450,
        236768,
        22541,
        735,
        3715,
        4945,
        6810,
        236749,
        236785,
        193983,
        4547,
        3618,
        54773,
        684,
        506,
        44751,
        563,
        531,
        26756,
        506,
        42442,
        5296,
        529,
        7767,
        236772,
        236770,
        236819,
        3636,
        528,
        13531,
        1024,
        496,
        236743,
        236770,
        236812,
        236772,
        1496,
        2846,
        532,
        8357,
        506,
        25432,
        607,
        506,
        7310,
        1624,
        18558,
        236761,
        1174,
        1938,
        563,
        13832,
        573,
        1237,
        2404,
        10221,
        531,
        3213,
        910,
        5405,
        532,
        4144,
        20054,
        33592,
        236761,
        669,
        44751,
        12765,
        16074,
        506,
        27187,
        529,
        3636,
        532,
        21558,
        3435,
        139978,
        6810,
        236749,
        236785,
        236749,
        22515,
        580,
        1041,
        3671,
        236764,
        625,
        236789,
        236751,
        3582,
        600,
        1624,
        14866,
        659,
        711,
        41923,
        7028,
        5459,
        13531,
        236761,
        669,
        22541,
        1494,
        4945,
        528,
        27071,
        532,
        57450,
        3600,
        600,
        1239,
        4106,
        964,
        3629,
        46462,
        531,
        506,
        6782,
        1624,
        1527,
        1913,
        506,
        2846,
        3505,
        236761,
        669,
        3553,
        528,
        3636,
        5773,
        528,
        506,
        3209,
        14069,
        62096,
        3342,
        10622,
        531,
        3050,
        506,
        14397,
        529,
        506,
        7003,
        532,
        5001,
        3342,
        7028,
        236761,
        669,
        44751,
        4728,
        496,
        63510,
        532,
        40878,
        5225,
        1595,
        531,
        17730,
        3996,
        131012,
        1262,
        6810,
        236749,
        236785,
        236749,
        229806,
        27242,
        5393,
        2540,
        236787,
        669,
        2471,
        563,
        24746,
        3582,
        236764,
        532,
        506,
        44358,
        5467,
        27879,
        531,
        506,
        3004,
        236761,
        669,
        2258,
        10165,
        563,
        11974,
        1456,
        531,
        2754,
        506,
        14889,
        529,
        3636,
        236761,
        669,
        1262,
        7412,
        531,
        577,
        13957,
        532,
        6212,
        528,
        496,
        4077,
        153819,
        6518,
        236761,
        564,
        1006,
        12081,
        528,
        1041,
        16823,
        1547,
        506,
        88308,
        1262,
        563,
        24267,
        532,
        3735,
        531,
        3050,
        236764,
        532,
        993,
        236789,
        236751,
        11893,
        57352,
        236761,
        3153,
        236764,
        506,
        4453,
        4945,
        2351,
        1546,
        2145,
        10050,
        236789,
        236745,
        15205,
        236764,
        837,
        11649,
        506,
        18510,
        529,
        506,
        3671,
        236761,
        1174,
        33235,
        531,
        496,
        8427,
        3718,
        10805,
        6317,
        1781,
        107,
        236783,
        107,
        2717
    ],
    "total_duration": 58331240310,
    "load_duration": 146167841,
    "prompt_eval_count": 550,
    "prompt_eval_duration": 825198703,
    "eval_count": 640,
    "eval_duration": 21331267363
}