{
    "tweet_id": "1429110786056654857",
    "computation_time": 33.693341970443726,
    "model": "gemma3:27b",
    "created_at": "2025-08-07T08:49:24.282639Z",
    "response": {
        "confidence": 95,
        "analysis": "The image is a bar graph depicting the estimated cost of COVID-19 hospitalizations for unvaccinated adults in the U.S. during June and July 2021. The y-axis represents cost in billions of dollars, ranging from 0 to 3 billion. The x-axis indicates the period: June 2021, July 2021, and combined June and July 2021. \n\nThe bar for June 2021 shows a cost of $0.7 billion. The bar for July 2021 demonstrates a significant increase to $1.5 billion. The combined June and July 2021 period shows the highest cost, reaching $2.3 billion. \n\nThe trend clearly indicates a substantial rise in hospitalization costs associated with unvaccinated adults during the summer of 2021. The increase from June to July is considerable, and the cumulative cost for the two months is even higher. The visualization strongly suggests that a significant financial burden is linked to hospitalizations of unvaccinated individuals.\n\nThe message the visualization is communicating is that unvaccinated COVID-19 patients placed a substantial economic burden on the US health system in June and July 2021, and that the costs rose significantly over that period. This data likely supports arguments for increased vaccination efforts and/or policies addressing the costs associated with preventable hospitalizations.\n\nBased on the analysis, the rising costs of hospitalizations for unvaccinated adults in the summer of 2021 represent a significant financial strain on the U.S. healthcare system. It reinforces the importance of vaccination as a cost-effective measure in mitigating the spread of COVID-19 and reducing healthcare expenditures. The image is very clear, and the data is straightforward, aligning perfectly with the provided caption, thus enhancing confidence in the interpretation. A slight confidence decrease is due to a lack of source information regarding the cost estimation methodology."
    },
    "done": true,
    "done_reason": "stop",
    "context": [
        105,
        2364,
        107,
        236840,
        3024,
        236772,
        236771,
        236842,
        109,
        3048,
        659,
        2238,
        614,
        2471,
        600,
        6097,
        886,
        653,
        919,
        151289,
        532,
        614,
        34043,
        44358,
        236761,
        108,
        818,
        44358,
        563,
        236787,
        623,
        2805,
        137953,
        7767,
        236772,
        236770,
        236819,
        6634,
        17238,
        2157,
        506,
        749,
        236761,
        236773,
        236761,
        2404,
        1458,
        47124,
        529,
        11092,
        107,
        2574,
        1411,
        16602,
        9731,
        38535,
        236761,
        2187,
        236786,
        37767,
        236786,
        602,
        137953,
        236772,
        59372,
        236772,
        102434,
        236772,
        13769,
        236772,
        1437,
        236772,
        236756,
        236772,
        236751,
        236772,
        16602,
        236772,
        9731,
        236772,
        36736,
        878,
        236772,
        1340,
        236772,
        145915,
        236786,
        237064,
        3056,
        108,
        11069,
        4209,
        563,
        531,
        236787,
        107,
        255968,
        236770,
        236761,
        255968,
        115863,
        506,
        3004,
        529,
        506,
        2471,
        532,
        506,
        44358,
        236761,
        107,
        255968,
        236778,
        236761,
        255968,
        82858,
        528,
        8052,
        1144,
        506,
        151289,
        2754,
        236761,
        49644,
        27570,
        236764,
        15067,
        236764,
        9935,
        236764,
        12669,
        236764,
        653,
        24786,
        1262,
        3298,
        236761,
        107,
        255968,
        236800,
        236761,
        255968,
        156022,
        506,
        151289,
        236787,
        2900,
        19317,
        740,
        577,
        9710,
        236881,
        2900,
        563,
        506,
        4547,
        3618,
        653,
        12882,
        506,
        151289,
        659,
        40122,
        236881,
        107,
        255968,
        236812,
        236761,
        255968,
        93000,
        822,
        1852,
        12882,
        2721,
        580,
        822,
        3671,
        236761,
        107,
        255968,
        236810,
        236761,
        255968,
        21796,
        822,
        10805,
        528,
        822,
        16823,
        580,
        496,
        5559,
        699,
        236743,
        236771,
        531,
        236743,
        236770,
        236771,
        236771,
        236764,
        1298,
        236743,
        236771,
        2820,
        999,
        2217,
        12081,
        657,
        784,
        236919,
        532,
        236743,
        236770,
        236771,
        236771,
        2820,
        999,
        133299,
        12081,
        1827,
        5393,
        1891,
        822,
        10805,
        6317,
        568,
        236744,
        236761,
        236759,
        1126,
        2471,
        29972,
        236764,
        57352,
        528,
        1262,
        236764,
        25000,
        607,
        44358,
        236764,
        4044,
        7476,
        108,
        3912,
        13868,
        236764,
        3582,
        236764,
        532,
        18997,
        528,
        822,
        15569,
        236761,
        39874,
        46020,
        11461,
        236761,
        108,
        7925,
        528,
        10434,
        6518,
        236764,
        1133,
        672,
        236787,
        107,
        236782,
        107,
        138,
        236775,
        58578,
        1083,
        623,
        217349,
        6317,
        699,
        4209,
        1523,
        236743,
        236810,
        5899,
        1590,
        827,
        107,
        138,
        236775,
        28263,
        1083,
        623,
        17993,
        9813,
        3671,
        3072,
        568,
        8071,
        3298,
        236743,
        236770,
        236964,
        236810,
        236768,
        5899,
        1590,
        827,
        107,
        236783,
        108,
        6294,
        711,
        3204,
        4658,
        1663,
        1032,
        1082,
        506,
        8373,
        2495,
        236761,
        3574,
        711,
        1879,
        20686,
        3723,
        657,
        506,
        6534,
        236761,
        107,
        106,
        107,
        105,
        4368,
        107,
        2717,
        3723,
        107,
        236782,
        107,
        138,
        236775,
        58578,
        1083,
        236743,
        236819,
        236810,
        236764,
        107,
        138,
        236775,
        28263,
        1083,
        623,
        818,
        2471,
        563,
        496,
        3029,
        3753,
        62223,
        506,
        9460,
        2157,
        529,
        7767,
        236772,
        236770,
        236819,
        6634,
        17238,
        573,
        176775,
        12795,
        528,
        506,
        749,
        236761,
        236773,
        236761,
        1913,
        5142,
        532,
        5505,
        236743,
        236778,
        236771,
        236778,
        236770,
        236761,
        669,
        570,
        236772,
        11569,
        9282,
        2157,
        528,
        47124,
        529,
        11092,
        236764,
        20027,
        699,
        236743,
        236771,
        531,
        236743,
        236800,
        7889,
        236761,
        669,
        1123,
        236772,
        11569,
        11387,
        506,
        2846,
        236787,
        5142,
        236743,
        236778,
        236771,
        236778,
        236770,
        236764,
        5505,
        236743,
        236778,
        236771,
        236778,
        236770,
        236764,
        532,
        9292,
        5142,
        532,
        5505,
        236743,
        236778,
        236771,
        236778,
        236770,
        236761,
        621,
        236749,
        236785,
        193983,
        3029,
        573,
        5142,
        236743,
        236778,
        236771,
        236778,
        236770,
        3831,
        496,
        2157,
        529,
        609,
        236771,
        236761,
        236832,
        7889,
        236761,
        669,
        3029,
        573,
        5505,
        236743,
        236778,
        236771,
        236778,
        236770,
        29350,
        496,
        3629,
        3553,
        531,
        609,
        236770,
        236761,
        236810,
        7889,
        236761,
        669,
        9292,
        5142,
        532,
        5505,
        236743,
        236778,
        236771,
        236778,
        236770,
        2846,
        3831,
        506,
        7310,
        2157,
        236764,
        17154,
        609,
        236778,
        236761,
        236800,
        7889,
        236761,
        621,
        236749,
        236785,
        193983,
        7003,
        8207,
        11387,
        496,
        14649,
        8570,
        528,
        103616,
        5384,
        5143,
        607,
        176775,
        12795,
        1913,
        506,
        5312,
        529,
        236743,
        236778,
        236771,
        236778,
        236770,
        236761,
        669,
        3553,
        699,
        5142,
        531,
        5505,
        563,
        13492,
        236764,
        532,
        506,
        38608,
        2157,
        573,
        506,
        1156,
        3794,
        563,
        1581,
        3715,
        236761,
        669,
        44751,
        12117,
        12205,
        600,
        496,
        3629,
        4867,
        18080,
        563,
        12809,
        531,
        6634,
        17238,
        529,
        176775,
        7010,
        6810,
        236749,
        236785,
        193983,
        3618,
        506,
        44751,
        563,
        40122,
        563,
        600,
        176775,
        7767,
        236772,
        236770,
        236819,
        4399,
        7006,
        496,
        14649,
        5527,
        18080,
        580,
        506,
        2590,
        2404,
        1458,
        528,
        5142,
        532,
        5505,
        236743,
        236778,
        236771,
        236778,
        236770,
        236764,
        532,
        600,
        506,
        5384,
        11076,
        8792,
        1024,
        600,
        2846,
        236761,
        1174,
        1262,
        4547,
        12765,
        12130,
        573,
        4869,
        30604,
        7880,
        532,
        236786,
        504,
        10034,
        25963,
        506,
        5384,
        5143,
        607,
        148528,
        6634,
        17238,
        6810,
        236749,
        236785,
        236749,
        22515,
        580,
        506,
        3671,
        236764,
        506,
        15213,
        5384,
        529,
        6634,
        17238,
        573,
        176775,
        12795,
        528,
        506,
        5312,
        529,
        236743,
        236778,
        236771,
        236778,
        236770,
        2754,
        496,
        3629,
        4867,
        9262,
        580,
        506,
        749,
        236761,
        236773,
        236761,
        16106,
        1458,
        236761,
        1030,
        113103,
        506,
        8020,
        529,
        30604,
        618,
        496,
        2157,
        236772,
        25931,
        4113,
        528,
        93389,
        506,
        7028,
        529,
        7767,
        236772,
        236770,
        236819,
        532,
        13471,
        16106,
        41750,
        236761,
        669,
        2471,
        563,
        1401,
        3582,
        236764,
        532,
        506,
        1262,
        563,
        24267,
        236764,
        120022,
        13275,
        607,
        506,
        3847,
        44358,
        236764,
        5478,
        36674,
        10805,
        528,
        506,
        16823,
        236761,
        562,
        6495,
        10805,
        11086,
        563,
        2779,
        531,
        496,
        6220,
        529,
        3738,
        1938,
        8859,
        506,
        2157,
        22851,
        26423,
        1781,
        107,
        236783,
        107,
        2717
    ],
    "total_duration": 33688314875,
    "load_duration": 49721958,
    "prompt_eval_count": 593,
    "prompt_eval_duration": 9566189416,
    "eval_count": 422,
    "eval_duration": 24071506875
}