{
    "tweet_id": "1316054009296359426",
    "computation_time": 57.62942385673523,
    "model": "gemma3:27b",
    "created_at": "2025-08-07T13:43:37.885371357Z",
    "response": {
        "confidence": 85,
        "analysis": "The image presents two line graphs depicting COVID-19 data for Lubbock County, Texas. The x-axis represents time, spanning from February 2021 to October 2021. The y-axis ranges from 0 to 800+, indicating the number of cases. The green line represents 'Daily Cases,' showing a generally increasing trend over time with significant peaks and valleys. The red line represents the '7-day average,' which smooths out the daily fluctuations. Below these lines is a faint dotted line representing the '14-day target', which appears to be at a constant value of about 25. The caption states that Lubbock County has the 10th highest 14-day positives in the US with 832 per 100k people. \n\nThe visualization highlights a significant surge in daily cases in late summer/early fall of 2021, with the 7-day average peaking at a high level. The constant dotted line representing the target is visually overwhelmed by the increasing trend of cases, suggesting that the target has been significantly exceeded. The sheer height of the green and red lines in comparison to the dotted line emphasizes the severity of the outbreak.",
        "misleading_info": {
            "is_misleading": true,
            "confidence_on_misleading": 80,
            "is_intentional": true,
            "confidence_on_intentional": 60,
            "why_misleading": "The visualization uses a severely truncated y-axis that exaggerates the increase in daily cases and makes the target appear insignificant.",
            "why_intentional": "While potentially unintentional, the choice of y-axis scale heavily manipulates the visual impact, which could be intentional to create a sense of alarm.",
            "misleading_aspects": [
                "The y-axis starts at a high value (approximately 150) instead of zero, making the increase in cases appear much more dramatic.",
                "The target line is almost invisible because of the vastly different y-axis scale, making it seem like the target is completely irrelevant.",
                "The caption stating a case rate of 832 per 100k does not align well with the visual, since the visualization only shows raw numbers.",
                "visualization_rethoric\": {\\\n    \"Information_Access_Rhetoric\": {\\\n      \"exists",
                true,
                "confidence",
                90,
                "description\": \"The choice to start the y-axis at a non-zero value drastically alters the perception of the data's magnitude and growth.",
                "supports_misleading",
                true,
                "why_supports_misleading\": \"By starting the y-axis at 150 instead of 0, the visualization exaggerates the changes in case numbers, making the increase appear much steeper and more alarming than it actually is.",
                "Provenance_Rhetorics\": {\\\n      \"exists",
                false,
                "confidence",
                20,
                "description\": \"There's no clear indication of the data source or methodology used to create the visualization.",
                "supports_misleading",
                false,
                "why_supports_misleading\": \"The lack of provenance information does not directly support the misleading aspects, but it does reduce the trustworthiness of the visualization.",
                "Mapping_Rhetoric\": {\\\n      \"exists",
                true,
                "confidence",
                80,
                "description\": \"The mapping of data to the y-axis is the primary source of the misleading effect, as the truncated axis distorts the visual representation of the data's magnitude.",
                "supports_misleading",
                true,
                "why_supports_misleading\": \"The choice of y-axis scale emphasizes the increase in cases at the expense of accurately representing the overall magnitude of the data.",
                "Linguistic_Based_Rhetoric\": {\\\n      \"exists",
                true,
                "confidence",
                60,
                "description\": \"The caption and axis labels frame the visualization, but the discrepancy between the caption and the visual scale amplifies the misleading effect.",
                "supports_misleading",
                true,
                "why_supports_misleading\": \"While the caption provides additional context, it doesn't correct the distortion caused by the truncated y-axis. This creates a disconnect between the numerical information and the visual representation.",
                "Procedural_Rhetoric\": {\\\n      \"exists",
                false,
                "confidence",
                20,
                "description\": \"The visualization is static, so there's no interactive element that could further manipulate the user's perception.",
                "supports_misleading",
                false,
                "why_supports_misleading\": \"There are no procedural elements that contribute to the misleading effect."
            ]
        },
        "visualization_rethoric": {
            "Information_Access_Rhetoric": {
                "exists": false,
                "confidence": 0,
                "description": "",
                "supports_misleading": false,
                "why_supports_misleading": ""
            },
            "Provenance_Rhetoric": {
                "exists": false,
                "confidence": 0,
                "description": "",
                "supports_misleading": false,
                "why_supports_misleading": ""
            },
            "Mapping_Rhetoric": {
                "exists": false,
                "confidence": 0,
                "description": "",
                "supports_misleading": false,
                "why_supports_misleading": ""
            },
            "Linguistic_Based_Rhetoric": {
                "exists": false,
                "confidence": 0,
                "description": "",
                "supports_misleading": false,
                "why_supports_misleading": ""
            },
            "Procedural_Rhetoric": {
                "exists": false,
                "confidence": 0,
                "description": "",
                "supports_misleading": false,
                "why_supports_misleading": ""
            }
        }
    },
    "done": true,
    "done_reason": "stop",
    "context": [
        105,
        2364,
        107,
        236840,
        3024,
        236772,
        236771,
        236842,
        109,
        3048,
        659,
        2238,
        614,
        2471,
        600,
        6097,
        886,
        653,
        919,
        151289,
        532,
        614,
        34043,
        44358,
        236761,
        107,
        818,
        44358,
        563,
        236787,
        623,
        236798,
        58282,
        945,
        5796,
        9539,
        815,
        506,
        236743,
        236770,
        236771,
        594,
        7310,
        236743,
        236770,
        236812,
        236772,
        1496,
        7767,
        236772,
        236770,
        236819,
        74477,
        528,
        506,
        749,
        236761,
        236773,
        1126,
        607,
        236743,
        236828,
        236800,
        236778,
        810,
        236743,
        236770,
        236771,
        236771,
        236767,
        1331,
        3056,
        108,
        3912,
        7039,
        236787,
        669,
        151289,
        1149,
        577,
        49028,
        236764,
        3477,
        53271,
        653,
        153044,
        236761,
        2195,
        2473,
        3014,
        102122,
        236764,
        106261,
        236764,
        653,
        1702,
        12871,
        600,
        3930,
        26998,
        506,
        1262,
        236761,
        108,
        11069,
        4209,
        563,
        531,
        236787,
        107,
        255968,
        236770,
        236761,
        255968,
        115863,
        506,
        3004,
        529,
        506,
        2471,
        532,
        506,
        44358,
        236761,
        107,
        255968,
        236778,
        236761,
        255968,
        82858,
        528,
        8052,
        1144,
        506,
        151289,
        2754,
        236761,
        49644,
        27570,
        236764,
        15067,
        236764,
        9935,
        236764,
        12669,
        236764,
        653,
        24786,
        1262,
        3298,
        236761,
        107,
        255968,
        236800,
        236761,
        255968,
        156022,
        506,
        151289,
        236787,
        2900,
        19317,
        740,
        577,
        9710,
        236881,
        2900,
        563,
        506,
        4547,
        3618,
        653,
        12882,
        506,
        151289,
        659,
        40122,
        236881,
        107,
        255968,
        236812,
        236761,
        255968,
        93000,
        822,
        1852,
        12882,
        2721,
        580,
        822,
        3671,
        236761,
        107,
        255968,
        236810,
        236761,
        255968,
        21796,
        822,
        10805,
        528,
        822,
        16823,
        580,
        496,
        5559,
        699,
        236743,
        236771,
        531,
        236743,
        236770,
        236771,
        236771,
        236764,
        1298,
        236743,
        236771,
        2820,
        999,
        2217,
        12081,
        657,
        784,
        236919,
        532,
        236743,
        236770,
        236771,
        236771,
        2820,
        999,
        133299,
        12081,
        1827,
        5393,
        1891,
        822,
        10805,
        6317,
        568,
        236744,
        236761,
        236759,
        1126,
        2471,
        29972,
        236764,
        57352,
        528,
        1262,
        236764,
        25000,
        607,
        44358,
        236764,
        4044,
        7476,
        107,
        255968,
        236825,
        236761,
        255968,
        111463,
        1805,
        13901,
        3363,
        506,
        151289,
        1149,
        577,
        49028,
        236764,
        3477,
        53271,
        653,
        684,
        18932,
        236761,
        5393,
        1891,
        822,
        28507,
        684,
        26242,
        531,
        3530,
        7426,
        4820,
        653,
        1702,
        12871,
        236761,
        10522,
        1966,
        506,
        44751,
        49028,
        768,
        822,
        10805,
        528,
        672,
        11179,
        563,
        1494,
        236761,
        107,
        255968,
        236832,
        236761,
        255968,
        137938,
        992,
        506,
        4458,
        529,
        44751,
        66412,
        1456,
        236764,
        768,
        1027,
        236761,
        6890,
        506,
        8514,
        529,
        506,
        3493,
        7157,
        4458,
        529,
        44751,
        66412,
        3847,
        657,
        506,
        1345,
        529,
        672,
        11172,
        236761,
        21429,
        600,
        541,
        733,
        659,
        3493,
        7157,
        4458,
        529,
        44751,
        66412,
        236787,
        8230,
        13863,
        221749,
        31444,
        236764,
        94523,
        831,
        221749,
        31444,
        236764,
        72174,
        221749,
        31444,
        236764,
        209284,
        236772,
        22515,
        221749,
        31444,
        236764,
        532,
        146829,
        1762,
        221749,
        31444,
        236761,
        1030,
        563,
        2653,
        600,
        7293,
        529,
        1239,
        4458,
        5510,
        531,
        506,
        151289,
        611,
        659,
        32187,
        236761,
        1701,
        1546,
        1722,
        611,
        8701,
        236764,
        2847,
        506,
        10805,
        528,
        822,
        11179,
        580,
        496,
        5559,
        699,
        236743,
        236771,
        531,
        236743,
        236770,
        236771,
        236771,
        236764,
        532,
        496,
        8652,
        15569,
        529,
        1217,
        625,
        16819,
        531,
        506,
        151289,
        528,
        2934,
        532,
        768,
        611,
        1751,
        625,
        12765,
        506,
        49028,
        10217,
        611,
        8385,
        528,
        1523,
        236743,
        236825,
        236761,
        109,
        11069,
        3072,
        531,
        1523,
        236743,
        236825,
        1921,
        992,
        50874,
        506,
        49028,
        236779,
        3906,
        2135,
        529,
        506,
        10434,
        3938,
        236761,
        107,
        255968,
        236772,
        255968,
        21796,
        822,
        10805,
        528,
        822,
        12207,
        529,
        506,
        151289,
        1646,
        49028,
        236764,
        580,
        496,
        5559,
        699,
        236743,
        236771,
        531,
        236743,
        236770,
        236771,
        236771,
        236761,
        107,
        140,
        236772,
        139,
        102752,
        3363,
        506,
        49028,
        10217,
        659,
        4547,
        46041,
        653,
        178192,
        236764,
        532,
        3136,
        822,
        10805,
        528,
        672,
        11179,
        580,
        496,
        5559,
        699,
        236743,
        236771,
        531,
        236743,
        236770,
        236771,
        236771,
        236761,
        107,
        255968,
        236772,
        255968,
        12721,
        3204,
        496,
        1694,
        529,
        49028,
        10217,
        618,
        2822,
        23974,
        600,
        49573,
        506,
        4820,
        600,
        5378,
        611,
        531,
        1751,
        506,
        44751,
        1149,
        577,
        49028,
        236761,
        108,
        3912,
        13868,
        236764,
        3582,
        236764,
        532,
        18997,
        528,
        822,
        15569,
        236761,
        39874,
        46020,
        11461,
        236761,
        108,
        7925,
        528,
        10434,
        6518,
        236764,
        1133,
        672,
        236787,
        107,
        236782,
        107,
        138,
        236775,
        58578,
        1083,
        623,
        217349,
        6317,
        699,
        4209,
        1523,
        236743,
        236810,
        5899,
        1590,
        827,
        107,
        138,
        236775,
        28263,
        1083,
        623,
        17993,
        9813,
        3671,
        3072,
        568,
        8071,
        3298,
        236743,
        236770,
        236964,
        236825,
        236768,
        5899,
        1590,
        827,
        107,
        138,
        236775,
        25714,
        26016,
        236779,
        3906,
        1083,
        642,
        236743,
        107,
        140,
        236775,
        511,
        236779,
        25714,
        26016,
        1083,
        623,
        236746,
        8538,
        17674,
        3363,
        611,
        1751,
        506,
        151289,
        659,
        49028,
        827,
        107,
        140,
        236775,
        58578,
        236779,
        498,
        236779,
        25714,
        26016,
        1083,
        623,
        217349,
        6317,
        699,
        4209,
        1523,
        236743,
        236825,
        5899,
        1590,
        236764,
        31470,
        822,
        10805,
        528,
        3363,
        506,
        151289,
        659,
        49028,
        653,
        711,
        827,
        107,
        140,
        236775,
        511,
        236779,
        133273,
        1083,
        623,
        236746,
        8538,
        17674,
        3363,
        611,
        1751,
        506,
        49028,
        10217,
        659,
        46041,
        827,
        107,
        255968,
        236775,
        58578,
        236779,
        498,
        236779,
        133273,
        1083,
        623,
        217349,
        6317,
        699,
        4209,
        1523,
        236743,
        236825,
        5899,
        1590,
        236764,
        31470,
        822,
        10805,
        528,
        3363,
        506,
        49028,
        10217,
        659,
        46041,
        653,
        178192,
        827,
        107,
        140,
        236775,
        36425,
        236779,
        25714,
        26016,
        1083,
        623,
        236746,
        2822,
        15569,
        529,
        3217,
        611,
        1751,
        506,
        151289,
        659,
        49028,
        827,
        107,
        255968,
        236775,
        36425,
        236779,
        133273,
        1083,
        623,
        236746,
        2822,
        15569,
        529,
        3217,
        611,
        1751,
        506,
        49028,
        10217,
        659,
        46041,
        653,
        178192,
        827,
        107,
        140,
        236775,
        25714,
        26016,
        236779,
        45660,
        236751,
        1083,
        870,
        107,
        142,
        236775,
        15721,
        6492,
        529,
        496,
        14846,
        49028,
        3408,
        827,
        107,
        142,
        236775,
        51208,
        49028,
        6084,
        236764,
        768,
        1027,
        236775,
        107,
        140,
        236842,
        107,
        138,
        236783,
        107,
        138,
        236775,
        148793,
        236779,
        500,
        15877,
        525,
        1083,
        642,
        107,
        140,
        236775,
        23415,
        236779,
        11942,
        236779,
        236794,
        4412,
        31444,
        1083,
        642,
        107,
        255968,
        138,
        236775,
        14751,
        1083,
        623,
        23470,
        17674,
        3363,
        672,
        1722,
        16819,
        531,
        506,
        151289,
        827,
        107,
        255968,
        138,
        236775,
        58578,
        1083,
        623,
        217349,
        6317,
        699,
        4209,
        1523,
        236743,
        236832,
        5899,
        1590,
        827,
        107,
        255968,
        138,
        236775,
        7777,
        1083,
        623,
        236746,
        8652,
        15569,
        529,
        1217,
        672,
        1722,
        16819,
        531,
        506,
        151289,
        827,
        107,
        255968,
        138,
        236775,
        43925,
        236779,
        25714,
        26016,
        1083,
        623,
        23470,
        17674,
        3363,
        672,
        1722,
        12765,
        506,
        49028,
        10217,
        8385,
        528,
        1523,
        236743,
        236825,
        827,
        107,
        255968,
        138,
        236775,
        36425,
        236779,
        43925,
        236779,
        25714,
        26016,
        1083,
        623,
        236746,
        8652,
        15569,
        529,
        1217,
        672,
        1722,
        12765,
        506,
        49028,
        10217,
        236764,
        768,
        11955,
        236775,
        107,
        255968,
        1263,
        107,
        140,
        236775,
        150558,
        236779,
        236794,
        4412,
        504,
        1229,
        1083,
        642,
        107,
        255968,
        138,
        236775,
        14751,
        1083,
        623,
        23470,
        17674,
        3363,
        672,
        1722,
        16819,
        531,
        506,
        151289,
        827,
        107,
        255968,
        138,
        236775,
        58578,
        1083,
        623,
        217349,
        6317,
        699,
        4209,
        1523,
        236743,
        236832,
        5899,
        1590,
        827,
        107,
        255968,
        138,
        236775,
        7777,
        1083,
        623,
        236746,
        8652,
        15569,
        529,
        1217,
        672,
        1722,
        16819,
        531,
        506,
        151289,
        827,
        107,
        255968,
        138,
        236775,
        43925,
        236779,
        25714,
        26016,
        1083,
        623,
        23470,
        17674,
        3363,
        672,
        1722,
        12765,
        506,
        49028,
        10217,
        8385,
        528,
        1523,
        236743,
        236825,
        827,
        107,
        255968,
        138,
        236775,
        36425,
        236779,
        43925,
        236779,
        25714,
        26016,
        1083,
        623,
        236746,
        8652,
        15569,
        529,
        1217,
        672,
        1722,
        12765,
        506,
        49028,
        10217,
        236764,
        768,
        11955,
        236775,
        107,
        255968,
        1263,
        107,
        140,
        236775,
        12282,
        236779,
        236794,
        4412,
        31444,
        1083,
        642,
        107,
        255968,
        138,
        236775,
        14751,
        1083,
        623,
        23470,
        17674,
        3363,
        672,
        1722,
        16819,
        531,
        506,
        151289,
        827,
        107,
        255968,
        138,
        236775,
        58578,
        1083,
        623,
        217349,
        6317,
        699,
        4209,
        1523,
        236743,
        236832,
        5899,
        1590,
        827,
        107,
        255968,
        138,
        236775,
        7777,
        1083,
        623,
        236746,
        8652,
        15569,
        529,
        1217,
        672,
        1722,
        16819,
        531,
        506,
        151289,
        827,
        107,
        255968,
        138,
        236775,
        43925,
        236779,
        25714,
        26016,
        1083,
        623,
        23470,
        17674,
        3363,
        672,
        1722,
        12765,
        506,
        49028,
        10217,
        8385,
        528,
        1523,
        236743,
        236825,
        827,
        107,
        255968,
        138,
        236775,
        36425,
        236779,
        43925,
        236779,
        25714,
        26016,
        1083,
        623,
        236746,
        8652,
        15569,
        529,
        1217,
        672,
        1722,
        12765,
        506,
        49028,
        10217,
        236764,
        768,
        11955,
        236775,
        107,
        255968,
        1263,
        107,
        140,
        236775,
        236798,
        223496,
        236779,
        22515,
        236779,
        236794,
        4412,
        31444,
        1083,
        642,
        107,
        255968,
        138,
        236775,
        14751,
        1083,
        623,
        23470,
        17674,
        3363,
        672,
        1722,
        16819,
        531,
        506,
        151289,
        827,
        107,
        255968,
        138,
        236775,
        58578,
        1083,
        623,
        217349,
        6317,
        699,
        4209,
        1523,
        236743,
        236832,
        5899,
        1590,
        827,
        107,
        255968,
        138,
        236775,
        7777,
        1083,
        623,
        236746,
        8652,
        15569,
        529,
        1217,
        672,
        1722,
        16819,
        531,
        506,
        151289,
        827,
        107,
        255968,
        138,
        236775,
        43925,
        236779,
        25714,
        26016,
        1083,
        623,
        23470,
        17674,
        3363,
        672,
        1722,
        12765,
        506,
        49028,
        10217,
        8385,
        528,
        1523,
        236743,
        236825,
        827,
        107,
        255968,
        138,
        236775,
        36425,
        236779,
        43925,
        236779,
        25714,
        26016,
        1083,
        623,
        236746,
        8652,
        15569,
        529,
        1217,
        672,
        1722,
        12765,
        506,
        49028,
        10217,
        236764,
        768,
        11955,
        236775,
        107,
        255968,
        1263,
        107,
        140,
        236775,
        234040,
        1762,
        236779,
        236794,
        4412,
        31444,
        1083,
        642,
        107,
        255968,
        138,
        236775,
        14751,
        1083,
        623,
        23470,
        17674,
        3363,
        672,
        1722,
        16819,
        531,
        506,
        151289,
        827,
        107,
        255968,
        138,
        236775,
        58578,
        1083,
        623,
        217349,
        6317,
        699,
        4209,
        1523,
        236743,
        236832,
        5899,
        1590,
        827,
        107,
        255968,
        138,
        236775,
        7777,
        1083,
        623,
        236746,
        8652,
        15569,
        529,
        1217,
        672,
        1722,
        16819,
        531,
        506,
        151289,
        827,
        107,
        255968,
        138,
        236775,
        43925,
        236779,
        25714,
        26016,
        1083,
        623,
        23470,
        17674,
        3363,
        672,
        1722,
        12765,
        506,
        49028,
        10217,
        8385,
        528,
        1523,
        236743,
        236825,
        827,
        107,
        255968,
        138,
        236775,
        36425,
        236779,
        43925,
        236779,
        25714,
        26016,
        1083,
        623,
        236746,
        8652,
        15569,
        529,
        1217,
        672,
        1722,
        12765,
        506,
        49028,
        10217,
        236764,
        768,
        11955,
        236775,
        107,
        255968,
        236783,
        107,
        138,
        236783,
        107,
        236783,
        108,
        6294,
        711,
        3204,
        4658,
        1663,
        1032,
        1082,
        506,
        8373,
        2495,
        236761,
        3574,
        711,
        1879,
        20686,
        3723,
        657,
        506,
        6534,
        236761,
        109,
        8291,
        563,
        614,
        21385,
        529,
        506,
        3493,
        7157,
        4458,
        529,
        44751,
        66412,
        236787,
        8230,
        13863,
        221749,
        31444,
        236764,
        94523,
        831,
        221749,
        31444,
        236764,
        72174,
        221749,
        31444,
        236764,
        209284,
        236772,
        22515,
        221749,
        31444,
        236764,
        532,
        146829,
        1762,
        221749,
        31444,
        236761,
        107,
        255968,
        236772,
        8230,
        13863,
        221749,
        31444,
        236787,
        10867,
        616,
        531,
        12871,
        1003,
        1144,
        1262,
        531,
        3204,
        236764,
        68442,
        236764,
        5957,
        236764,
        653,
        27834,
        236761,
        3143,
        12871,
        6230,
        1144,
        506,
        31457,
        17149,
        532,
        837,
        9935,
        653,
        67966,
        659,
        35630,
        236761,
        107,
        255968,
        236772,
        94523,
        831,
        221749,
        31444,
        236787,
        7361,
        1090,
        531,
        1217,
        496,
        44751,
        83043,
        106980,
        236764,
        1288,
        618,
        684,
        47003,
        7021,
        236764,
        26804,
        4615,
        236764,
        28830,
        19262,
        236764,
        653,
        2440,
        26423,
        653,
        20345,
        236761,
        107,
        255968,
        236772,
        72174,
        221749,
        31444,
        236787,
        799,
        4477,
        2061,
        1217,
        1262,
        2979,
        659,
        28700,
        1131,
        7426,
        4065,
        1288,
        618,
        2939,
        236764,
        2425,
        236764,
        5559,
        236764,
        50232,
        236764,
        653,
        2258,
        236761,
        1174,
        740,
        2619,
        20622,
        653,
        6230,
        25708,
        6998,
        1144,
        506,
        10445,
        1262,
        106673,
        236761,
        107,
        255968,
        236772,
        209284,
        236772,
        22515,
        221749,
        31444,
        236787,
        65284,
        5192,
        4820,
        1133,
        19293,
        236764,
        12972,
        236764,
        62708,
        236764,
        653,
        100264,
        531,
        8214,
        16823,
        236761,
        35632,
        5132,
        50232,
        236764,
        82519,
        236764,
        139429,
        4137,
        236764,
        653,
        1032,
        22323,
        61842,
        236761,
        107,
        255968,
        236772,
        146829,
        1762,
        221749,
        31444,
        236787,
        7361,
        1090,
        531,
        9553,
        532,
        17042,
        1702,
        236764,
        1288,
        618,
        3678,
        8208,
        236764,
        18774,
        236764,
        653,
        53771,
        236761,
        3143,
        4065,
        8214,
        1217,
        5089,
        11327,
        506,
        1262,
        532,
        740,
        7630,
        837,
        23304,
        901,
        5370,
        236761,
        107,
        106,
        107,
        105,
        4368,
        107,
        2717,
        3723,
        107,
        236782,
        107,
        138,
        236775,
        58578,
        1083,
        236743,
        236828,
        236810,
        236764,
        107,
        138,
        236775,
        28263,
        1083,
        623,
        818,
        2471,
        15060,
        1156,
        1757,
        21338,
        62223,
        7767,
        236772,
        236770,
        236819,
        1262,
        573,
        43433,
        153412,
        5796,
        236764,
        9539,
        236761,
        669,
        1123,
        236772,
        11569,
        9282,
        990,
        236764,
        50317,
        699,
        7250,
        236743,
        236778,
        236771,
        236778,
        236770,
        531,
        6198,
        236743,
        236778,
        236771,
        236778,
        236770,
        236761,
        669,
        570,
        236772,
        11569,
        21280,
        699,
        236743,
        236771,
        531,
        236743,
        236828,
        236771,
        236771,
        36149,
        17674,
        506,
        1548,
        529,
        3636,
        236761,
        669,
        3826,
        1757,
        9282,
        756,
        42362,
        50697,
        6945,
        6807,
        496,
        6816,
        5683,
        7003,
        1024,
        990,
        607,
        3629,
        23338,
        532,
        70914,
        236761,
        669,
        2604,
        1757,
        9282,
        506,
        756,
        236832,
        236772,
        1496,
        4398,
        6945,
        837,
        7080,
        236751,
        855,
        506,
        6376,
        30217,
        236761,
        30791,
        1239,
        4463,
        563,
        496,
        44770,
        42825,
        1757,
        13855,
        506,
        756,
        236770,
        236812,
        236772,
        1496,
        3328,
        963,
        837,
        7412,
        531,
        577,
        657,
        496,
        4512,
        1550,
        529,
        1003,
        236743,
        236778,
        236810,
        236761,
        669,
        44358,
        5022,
        600,
        43433,
        153412,
        5796,
        815,
        506,
        236743,
        236770,
        236771,
        594,
        7310,
        236743,
        236770,
        236812,
        236772,
        1496,
        74477,
        528,
        506,
        2590,
        607,
        236743,
        236828,
        236800,
        236778,
        810,
        236743,
        236770,
        236771,
        236771,
        236767,
        1331,
        236761,
        621,
        236749,
        236785,
        193983,
        44751,
        20756,
        496,
        3629,
        19902,
        528,
        6376,
        3636,
        528,
        5226,
        5312,
        236786,
        47276,
        3798,
        529,
        236743,
        236778,
        236771,
        236778,
        236770,
        236764,
        607,
        506,
        236743,
        236832,
        236772,
        1496,
        4398,
        145739,
        657,
        496,
        1494,
        1984,
        236761,
        669,
        4512,
        42825,
        1757,
        13855,
        506,
        3328,
        563,
        40878,
        46002,
        684,
        506,
        5683,
        7003,
        529,
        3636,
        236764,
        22169,
        600,
        506,
        3328,
        815,
        1010,
        8792,
        36774,
        236761,
        669,
        37501,
        3558,
        529,
        506,
        3826,
        532,
        2604,
        4463,
        528,
        9960,
        531,
        506,
        42825,
        1757,
        58811,
        506,
        33326,
        529,
        506,
        33151,
        10498,
        107,
        138,
        236775,
        25714,
        26016,
        236779,
        3906,
        1083,
        642,
        107,
        140,
        236775,
        511,
        236779,
        25714,
        26016,
        1083,
        1847,
        236764,
        107,
        140,
        236775,
        58578,
        236779,
        498,
        236779,
        25714,
        26016,
        1083,
        236743,
        236828,
        236771,
        236764,
        107,
        140,
        236775,
        511,
        236779,
        133273,
        1083,
        236743,
        236825,
        236771,
        236764,
        107,
        140,
        236775,
        58578,
        236779,
        498,
        236779,
        133273,
        1083,
        236743,
        236825,
        236771,
        236764,
        107,
        140,
        236775,
        36425,
        236779,
        25714,
        26016,
        1083,
        623,
        818,
        44751,
        6178,
        496,
        35971,
        29839,
        570,
        236772,
        11569,
        600,
        45895,
        1090,
        506,
        3553,
        528,
        6376,
        3636,
        532,
        3590,
        506,
        3328,
        3196,
        61061,
        10498,
        107,
        140,
        236775,
        36425,
        236779,
        133273,
        1083,
        623,
        8409,
        14846,
        178192,
        236764,
        506,
        5313,
        529,
        570,
        236772,
        11569,
        5559,
        18677,
        15108,
        24003,
        506,
        7426,
        4100,
        236764,
        837,
        1451,
        577,
        46041,
        531,
        2619,
        496,
        5113,
        529,
        16605,
        10498,
        107,
        140,
        236775,
        25714,
        26016,
        236779,
        45660,
        236751,
        1083,
        870,
        107,
        142,
        236775,
        818,
        570,
        236772,
        11569,
        9857,
        657,
        496,
        1494,
        1550,
        568,
        78470,
        236743,
        236770,
        236810,
        236771,
        236768,
        5205,
        529,
        5743,
        236764,
        3043,
        506,
        3553,
        528,
        3636,
        3196,
        1623,
        919,
        20997,
        10498,
        107,
        142,
        236775,
        818,
        3328,
        1757,
        563,
        4180,
        35538,
        1547,
        529,
        506,
        69967,
        1607,
        570,
        236772,
        11569,
        5559,
        236764,
        3043,
        625,
        4483,
        1133,
        506,
        3328,
        563,
        6269,
        49106,
        10498,
        107,
        142,
        236775,
        818,
        44358,
        29354,
        496,
        1624,
        3136,
        529,
        236743,
        236828,
        236800,
        236778,
        810,
        236743,
        236770,
        236771,
        236771,
        236767,
        1677,
        711,
        8913,
        1388,
        607,
        506,
        7426,
        236764,
        2338,
        506,
        44751,
        1186,
        3831,
        10445,
        4945,
        1781,
        107,
        140,
        236842,
        107,
        138,
        1263,
        107,
        138,
        236775,
        148793,
        236779,
        500,
        15877,
        525,
        1083,
        642,
        107,
        140,
        236775,
        23415,
        236779,
        11942,
        236779,
        236794,
        4412,
        31444,
        1083,
        642,
        107,
        142,
        236775,
        14751,
        1083,
        1847,
        236764,
        107,
        142,
        236775,
        58578,
        1083,
        236743,
        236819,
        236771,
        236764,
        107,
        142,
        236775,
        7777,
        1083,
        623,
        818,
        5313,
        531,
        1502,
        506,
        570,
        236772,
        11569,
        657,
        496,
        1908,
        236772,
        13321,
        1550,
        54157,
        91395,
        506,
        25708,
        529,
        506,
        1262,
        236789,
        236751,
        14889,
        532,
        3877,
        10498,
        107,
        142,
        236775,
        43925,
        236779,
        25714,
        26016,
        1083,
        1847,
        236764,
        107,
        142,
        236775,
        36425,
        236779,
        43925,
        236779,
        25714,
        26016,
        1083,
        623,
        2292,
        6250,
        506,
        570,
        236772,
        11569,
        657,
        236743,
        236770,
        236810,
        236771,
        5205,
        529,
        236743,
        236771,
        236764,
        506,
        44751,
        45895,
        1090,
        506,
        3731,
        528,
        1624,
        4945,
        236764,
        3043,
        506,
        3553,
        3196,
        1623,
        145996,
        532,
        919,
        75851,
        1082,
        625,
        3643,
        563,
        1781,
        107,
        140,
        1263,
        107,
        140,
        236775,
        150558,
        236779,
        236794,
        4412,
        504,
        1229,
        1083,
        642,
        107,
        142,
        236775,
        14751,
        1083,
        2416,
        236764,
        107,
        142,
        236775,
        58578,
        1083,
        236743,
        236778,
        236771,
        236764,
        107,
        142,
        236775,
        7777,
        1083,
        623,
        3810,
        236789,
        236751,
        951,
        3582,
        25779,
        529,
        506,
        1262,
        3738,
        653,
        26423,
        1456,
        531,
        2619,
        506,
        44751,
        10498,
        107,
        142,
        236775,
        43925,
        236779,
        25714,
        26016,
        1083,
        2416,
        236764,
        107,
        142,
        236775,
        36425,
        236779,
        43925,
        236779,
        25714,
        26016,
        1083,
        623,
        818,
        6220,
        529,
        127389,
        1938,
        1677,
        711,
        5467,
        1894,
        506,
        49028,
        10217,
        236764,
        840,
        625,
        1677,
        6439,
        506,
        106980,
        529,
        506,
        44751,
        1781,
        107,
        140,
        1263,
        107,
        140,
        236775,
        12282,
        236779,
        236794,
        4412,
        31444,
        1083,
        642,
        107,
        142,
        236775,
        14751,
        1083,
        1847,
        236764,
        107,
        142,
        236775,
        58578,
        1083,
        236743,
        236828,
        236771,
        236764,
        107,
        142,
        236775,
        7777,
        1083,
        623,
        818,
        15468,
        529,
        1262,
        531,
        506,
        570,
        236772,
        11569,
        563,
        506,
        5905,
        3738,
        529,
        506,
        49028,
        1763,
        236764,
        618,
        506,
        29839,
        9485,
        1442,
        41470,
        506,
        7426,
        10065,
        529,
        506,
        1262,
        236789,
        236751,
        14889,
        10498,
        107,
        142,
        236775,
        43925,
        236779,
        25714,
        26016,
        1083,
        1847,
        236764,
        107,
        142,
        236775,
        36425,
        236779,
        43925,
        236779,
        25714,
        26016,
        1083,
        623,
        818,
        5313,
        529,
        570,
        236772,
        11569,
        5559,
        58811,
        506,
        3553,
        528,
        3636,
        657,
        506,
        18766,
        529,
        23704,
        13855,
        506,
        6782,
        14889,
        529,
        506,
        1262,
        1781,
        107,
        140,
        1263,
        107,
        140,
        236775,
        236798,
        223496,
        236779,
        22515,
        236779,
        236794,
        4412,
        31444,
        1083,
        642,
        107,
        142,
        236775,
        14751,
        1083,
        1847,
        236764,
        107,
        142,
        236775,
        58578,
        1083,
        236743,
        236825,
        236771,
        236764,
        107,
        142,
        236775,
        7777,
        1083,
        623,
        818,
        44358,
        532,
        9485,
        12972,
        5528,
        506,
        44751,
        236764,
        840,
        506,
        59725,
        1534,
        506,
        44358,
        532,
        506,
        7426,
        5559,
        10870,
        11427,
        506,
        49028,
        1763,
        10498,
        107,
        142,
        236775,
        43925,
        236779,
        25714,
        26016,
        1083,
        1847,
        236764,
        107,
        142,
        236775,
        36425,
        236779,
        43925,
        236779,
        25714,
        26016,
        1083,
        623,
        8409,
        506,
        44358,
        4728,
        4767,
        4403,
        236764,
        625,
        4038,
        236789,
        236745,
        4338,
        506,
        36744,
        7321,
        684,
        506,
        29839,
        570,
        236772,
        11569,
        236761,
        1174,
        14004,
        496,
        46096,
        1534,
        506,
        16688,
        1938,
        532,
        506,
        7426,
        10065,
        1781,
        107,
        140,
        1263,
        107,
        140,
        236775,
        234040,
        1762,
        236779,
        236794,
        4412,
        31444,
        1083,
        642,
        107,
        142,
        236775,
        14751,
        1083,
        2416,
        236764,
        107,
        142,
        236775,
        58578,
        1083,
        236743,
        236778,
        236771,
        236764,
        107,
        142,
        236775,
        7777,
        1083,
        623,
        818,
        44751,
        563,
        2002,
        236764,
        834,
        993,
        236789,
        236751,
        951,
        21931,
        3408,
        600,
        1451,
        3342,
        52266,
        506,
        2430,
        236789,
        236751,
        25708,
        10498,
        107,
        142,
        236775,
        43925,
        236779,
        25714,
        26016,
        1083,
        2416,
        236764,
        107,
        142,
        236775,
        36425,
        236779,
        43925,
        236779,
        25714,
        26016,
        1083,
        623,
        3810,
        659,
        951,
        63384,
        4820,
        600,
        13157,
        531,
        506,
        49028,
        1763,
        1781,
        107,
        140,
        236783,
        107,
        138,
        236783,
        107,
        236783,
        107,
        2717
    ],
    "total_duration": 57608742067,
    "load_duration": 138448786,
    "prompt_eval_count": 1958,
    "prompt_eval_duration": 1935073900,
    "eval_count": 1081,
    "eval_duration": 36516113618
}